odoo/addons/stock_picking_group_by_partner_by_carrier_force_move_type/README.rst
odoo/addons/stock_picking_group_by_partner_by_carrier_force_move_type/__init__.py
odoo/addons/stock_picking_group_by_partner_by_carrier_force_move_type/__manifest__.py
odoo/addons/stock_picking_group_by_partner_by_carrier_force_move_type/i18n/es_AR.po
odoo/addons/stock_picking_group_by_partner_by_carrier_force_move_type/i18n/it.po
odoo/addons/stock_picking_group_by_partner_by_carrier_force_move_type/i18n/stock_picking_group_by_partner_by_carrier_force_move_type.pot
odoo/addons/stock_picking_group_by_partner_by_carrier_force_move_type/i18n/stock_picking_type_shipping_policy_group_by.pot
odoo/addons/stock_picking_group_by_partner_by_carrier_force_move_type/models/__init__.py
odoo/addons/stock_picking_group_by_partner_by_carrier_force_move_type/models/stock_move.py
odoo/addons/stock_picking_group_by_partner_by_carrier_force_move_type/readme/CONTRIBUTORS.md
odoo/addons/stock_picking_group_by_partner_by_carrier_force_move_type/readme/CREDITS.md
odoo/addons/stock_picking_group_by_partner_by_carrier_force_move_type/readme/DESCRIPTION.md
odoo/addons/stock_picking_group_by_partner_by_carrier_force_move_type/static/description/icon.png
odoo/addons/stock_picking_group_by_partner_by_carrier_force_move_type/static/description/index.html
odoo/addons/stock_picking_group_by_partner_by_carrier_force_move_type/tests/__init__.py
odoo/addons/stock_picking_group_by_partner_by_carrier_force_move_type/tests/test_stock_picking_type_force_move_type.py
odoo_addon_stock_picking_group_by_partner_by_carrier_force_move_type-18.0.1.0.0.2.dist-info/METADATA
odoo_addon_stock_picking_group_by_partner_by_carrier_force_move_type-18.0.1.0.0.2.dist-info/WHEEL
odoo_addon_stock_picking_group_by_partner_by_carrier_force_move_type-18.0.1.0.0.2.dist-info/top_level.txt
odoo_addon_stock_picking_group_by_partner_by_carrier_force_move_type-18.0.1.0.0.2.dist-info/RECORD
